pyzbar/__init__.py
pyzbar/pyzbar.py
pyzbar/pyzbar_error.py
pyzbar/wrapper.py
pyzbar/zbar_library.py
pyzbar/scripts/__init__.py
pyzbar/scripts/read_zbar.py
pyzbar/tests/__init__.py
pyzbar/tests/code128.png
pyzbar/tests/empty.png
pyzbar/tests/qrcode.png
pyzbar/tests/test_pyzbar.py
pyzbar/tests/test_read_zbar.py
pyzbar/tests/test_zbar_library.py
pyzbar-0.1.5.data/scripts/read_zbar.py
pyzbar-0.1.5.dist-info/DESCRIPTION.rst
pyzbar-0.1.5.dist-info/METADATA
pyzbar-0.1.5.dist-info/RECORD
pyzbar-0.1.5.dist-info/WHEEL
pyzbar-0.1.5.dist-info/entry_points.txt
pyzbar-0.1.5.dist-info/metadata.json
pyzbar-0.1.5.dist-info/top_level.txt
